gcs/__init__.py
gcs/client.py
gcs/path.py
pycloudops-0.0.3.dist-info/METADATA
pycloudops-0.0.3.dist-info/WHEEL
pycloudops-0.0.3.dist-info/top_level.txt
pycloudops-0.0.3.dist-info/RECORD
