Metadata-Version: 2.1
Name: pycloudops
Version: 0.0.3
Summary: PyCloudOps serves to operate different cloud providers
Author: Endrit Berisha
Author-email: endritpb@gmail.com
Keywords: python,cloud,operations,path
Classifier: Development Status :: 3 - Alpha
Classifier: Intended Audience :: Education
Classifier: Programming Language :: Python :: 2
Classifier: Programming Language :: Python :: 3
Classifier: Operating System :: MacOS :: MacOS X
Classifier: Operating System :: Microsoft :: Windows
Requires-Dist: google-cloud-storage
